{
  "EUR/USD": 1.09921,
  "EUR/AUD": 1.6329,
  "EUR/GBP": 0.8564,
  "EUR/NZD": 1.77249,
  "EUR/CAD": 1.44967,
  "EUR/CHF": 0.95353,
  "EUR/JPY": 155.075,
  "EUR/HKD": 8.571,
  "EUR/SGD": 1.46297,
  "USD/EUR": 0.9097,
  "USD/AUD": 1.48529,
  "USD/GBP": 0.77926,
  "USD/NZD": 1.6125,
  "USD/CAD": 1.31891,
  "USD/CHF": 0.86748,
  "USD/JPY": 141.089,
  "USD/HKD": 7.80226,
  "USD/SGD": 1.33109,
  "AUD/EUR": 0.61233,
  "AUD/USD": 0.67308,
  "AUD/GBP": 0.52416,
  "AUD/NZD": 1.08553,
  "AUD/CAD": 0.88772,
  "AUD/CHF": 0.58391,
  "AUD/JPY": 94.96,
  "AUD/HKD": 5.244,
  "AUD/SGD": 0.89602,
  "GBP/EUR": 1.16751,
  "GBP/USD": 1.2835,
  "GBP/AUD": 1.90657,
  "GBP/NZD": 2.06953,
  "GBP/CAD": 1.6927,
  "GBP/CHF": 1.1133,
  "GBP/JPY": 181.076,
  "GBP/HKD": 10.013,
  "GBP/SGD": 1.70838,
  "NZD/EUR": 0.56401,
  "NZD/USD": 0.61999,
  "NZD/AUD": 0.92098,
  "NZD/GBP": 0.48301,
  "NZD/CAD": 0.81782,
  "NZD/CHF": null,
  "NZD/JPY": null,
  "NZD/HKD": null,
  "NZD/SGD": null,
  "CAD/EUR": null,
  "CAD/USD": null,
  "CAD/AUD": null,
  "CAD/GBP": null,
  "CAD/NZD": null,
  "CAD/CHF": null,
  "CAD/JPY": null,
  "CAD/HKD": null,
  "CAD/SGD": null,
  "CHF/EUR": null,
  "CHF/USD": null,
  "CHF/AUD": null,
  "CHF/GBP": null,
  "CHF/NZD": null,
  "CHF/CAD": null,
  "CHF/JPY": null,
  "CHF/HKD": null,
  "CHF/SGD": null,
  "JPY/EUR": null,
  "JPY/USD": null,
  "JPY/AUD": null,
  "JPY/GBP": null,
  "JPY/NZD": null,
  "JPY/CAD": null,
  "JPY/CHF": null,
  "JPY/HKD": null,
  "JPY/SGD": null,
  "HKD/EUR": null,
  "HKD/USD": null,
  "HKD/AUD": null,
  "HKD/GBP": null,
  "HKD/NZD": null,
  "HKD/CAD": null,
  "HKD/CHF": null,
  "HKD/JPY": null,
  "HKD/SGD": null,
  "SGD/EUR": null,
  "SGD/USD": null,
  "SGD/AUD": null,
  "SGD/GBP": null,
  "SGD/NZD": null,
  "SGD/CAD": null,
  "SGD/CHF": null,
  "SGD/JPY": null,
  "SGD/HKD": null,
  "CNY/EUR": null,
  "CNY/USD": null,
  "CNY/AUD": null,
  "CNY/GBP": null,
  "CNY/NZD": null,
  "CNY/CAD": null,
  "CNY/CHF": null,
  "CNY/JPY": null,
  "CNY/HKD": null,
  "CNY/SGD": null
}